LXIpxm78xx/__init__.py
examples/Example_41-620_FunctionGenerator.py
examples/Example_41-743_PowerSupply.py
examples/Example_Attenuator.py
examples/Example_BatterySimulator.py
examples/Example_CurrentLoopSimulator.py
examples/Example_DIO_Mux_card_piplx_LXI_PXI.py
examples/Example_Discovery.py
examples/Example_ListCards.py
examples/Example_Matrix.py
examples/Example_Matrix_SetCrosspointRange.py
examples/Example_MultiUser.py
examples/Example_OpenByAlias.py
examples/Example_PXM78xx.py
examples/Example_PowerSequencer.py
examples/Example_PrecisionResistor.py
examples/Example_ReleaseSessions.py
examples/Example_Resolver.py
examples/Example_StrainGauge.py
examples/Example_SubunitStates.py
examples/Example_Switching.py
examples/Example_Thermocouple.py
examples/41-450/Comparator_41-43-450_Example.py
examples/41-625/Example_ArbitraryWave_Generation.py
examples/41-625/Example_MultiChannel_Generation.py
examples/41-625/Example_Pulse_Generation.py
examples/41-625/Example_Sine_Generation.py
examples/41-625/Example_Trigger.py
pi620lx/__init__.py
pi743lx/__init__.py
pilxi/__init__.py
pilxi-5.7.dist-info/licenses/LICENSE.txt
pipslx/__init__.py
pilxi-5.7.dist-info/METADATA
pilxi-5.7.dist-info/WHEEL
pilxi-5.7.dist-info/top_level.txt
pilxi-5.7.dist-info/RECORD
