Metadata-Version: 2.4
Name: Pilxi
Version: 5.7
Summary: Python wrapper Library for Pickering LXI ClientBridge driver
Home-page: 
Author: Pickering Interfaces
Author-email: Pickering Interfaces <support@pickeringtest.com>
License: Copyright (c) 2017-2025 Pickering Interfaces Ltd.
Project-URL: homepage, https://pickeringtest.info/downloads/drivers/Sys60/
License-File: LICENSE.txt
Dynamic: author
Dynamic: license-file
